Metadata-Version: 2.1
Name: geneabacus
Version: 0.3.2
Summary: Python IO functions for GeneAbacus
Home-page: https://git.sr.ht/~vejnar/GeneAbacus-python
Author: Charles E. Vejnar
License: Mozilla Public License 2.0 (MPL 2.0)
Requires-Python: >=3.8
License-File: LICENSE
